num2farsiword/__init__.py
num2farsiword/num_to_word.py
num2farsiword-0.0.1.dist-info/LICENSE
num2farsiword-0.0.1.dist-info/METADATA
num2farsiword-0.0.1.dist-info/WHEEL
num2farsiword-0.0.1.dist-info/top_level.txt
num2farsiword-0.0.1.dist-info/RECORD
