Metadata-Version: 2.1
Name: num2farsiword
Version: 0.0.1
Summary: This package convert numbers to farsi words
Home-page: https://github.com/pypa/sampleproject
Author: Amir Hossein Pakdel
Author-email: amir.pakdel1378@yahoo.com
License: UNKNOWN
Project-URL: Bug Tracker, https://github.com/pypa/sampleproject/issues
Platform: UNKNOWN
Classifier: Programming Language :: Python :: 3
Classifier: License :: OSI Approved :: MIT License
Classifier: Operating System :: OS Independent
Requires-Python: >=3.6
License-File: LICENSE
